tinyfilter/__init__.py
tinyfilter-1.0.2.dist-info/METADATA
tinyfilter-1.0.2.dist-info/WHEEL
tinyfilter-1.0.2.dist-info/entry_points.txt
tinyfilter-1.0.2.dist-info/licenses/LICENSE
tinyfilter-1.0.2.dist-info/RECORD
