Metadata-Version: 2.1
Name: tinyfilter
Version: 1.0.2
Summary: tinyfilter is the computer vision equivalent to micrograd. It convert images into ASCII art using the principles of CNNs (convolutional neural networks).
Project-URL: Homepage, https://github.com/zroe1/tinyfilter/tree/main
Author-email: Zephaniah Roe <zroe@uchicago.edu>
License-File: LICENSE
Classifier: License :: OSI Approved :: MIT License
Classifier: Operating System :: OS Independent
Classifier: Programming Language :: Python :: 3
Requires-Python: >=3.7
Requires-Dist: numpy~=1.25.0
Requires-Dist: pillow
